<?xml version="1.0" encoding="utf-8" ?>
<dwsync>
<file name="banner-bg.jpg" server="C:/wamp/www/relacom/" local="128959967520000000" remote="128959967520000000" />
<file name="banner.jpg" server="C:/wamp/www/relacom/" local="128959988420000000" remote="128959988420000000" />
<file name="dotted-line.gif" server="C:/wamp/www/relacom/" local="128967983440000000" remote="128967983440000000" />
<file name="feature-botm-crv.jpg" server="C:/wamp/www/relacom/" local="128967992680000000" remote="128967992680000000" />
<file name="feature-top-crv.jpg" server="C:/wamp/www/relacom/" local="128967992280000000" remote="128967992280000000" />
<file name="foter-bg.jpg" server="C:/wamp/www/relacom/" local="128968003880000000" remote="128968003880000000" />
<file name="leftpan-btm-crv.jpg" server="C:/wamp/www/relacom/" local="128968009880000000" remote="128968009880000000" />
<file name="leftpan-top-crv.jpg" server="C:/wamp/www/relacom/" local="128968010060000000" remote="128968010060000000" />
<file name="logo-bg-bot.jpg" server="C:/wamp/www/relacom/" local="128959971640000000" remote="128959971640000000" />
<file name="logo-bg-top.jpg" server="C:/wamp/www/relacom/" local="128959971060000000" remote="128959971060000000" />
<file name="menu-bg-on.jpg" server="C:/wamp/www/relacom/" local="128959975880000000" remote="128959975880000000" />
<file name="menu-bg.jpg" server="C:/wamp/www/relacom/" local="128959975420000000" remote="128959975420000000" />
<file name="more-bg.gif" server="C:/wamp/www/relacom/" local="128967988320000000" remote="128967988320000000" />
<file name="news-pic.jpg" server="C:/wamp/www/relacom/" local="128968012860000000" remote="128968012860000000" />
<file name="right-panel-crv.gif" server="C:/wamp/www/relacom/" local="128967976220000000" remote="128967976220000000" />
<file name="round-bullet.gif" server="C:/wamp/www/relacom/" local="128968013840000000" remote="128968013840000000" />
<file name="star-icon.gif" server="C:/wamp/www/relacom/" local="128967981200000000" remote="128967981200000000" />
<file name="banner-bg.jpg" server="C:/wamp/www/relacom" local="128959967520000000" remote="128959967520000000" />
<file name="logo-bg-bot.jpg" server="C:/wamp/www/relacom" local="128959971640000000" remote="128959971640000000" />
<file name="logo-bg-top.jpg" server="C:/wamp/www/relacom" local="128959971060000000" remote="128959971060000000" />
<file name="menu-bg.jpg" server="C:/wamp/www/relacom" local="128959975420000000" remote="128959975420000000" />
<file name="menu-bg-on.jpg" server="C:/wamp/www/relacom" local="128959975880000000" remote="128959975880000000" />
<file name="banner.jpg" server="C:/wamp/www/relacom" local="128959988420000000" remote="128959988420000000" />
<file name="right-panel-crv.gif" server="C:/wamp/www/relacom" local="128967976220000000" remote="128967976220000000" />
<file name="star-icon.gif" server="C:/wamp/www/relacom" local="128967981200000000" remote="128967981200000000" />
<file name="dotted-line.gif" server="C:/wamp/www/relacom" local="128967983440000000" remote="128967983440000000" />
<file name="more-bg.gif" server="C:/wamp/www/relacom" local="128967988320000000" remote="128967988320000000" />
<file name="feature-top-crv.jpg" server="C:/wamp/www/relacom" local="128967992280000000" remote="128967992280000000" />
<file name="feature-botm-crv.jpg" server="C:/wamp/www/relacom" local="128967992680000000" remote="128967992680000000" />
<file name="foter-bg.jpg" server="C:/wamp/www/relacom" local="128968003880000000" remote="128968003880000000" />
<file name="leftpan-top-crv.jpg" server="C:/wamp/www/relacom" local="128968010060000000" remote="128968010060000000" />
<file name="leftpan-btm-crv.jpg" server="C:/wamp/www/relacom" local="128968009880000000" remote="128968009880000000" />
<file name="round-bullet.gif" server="C:/wamp/www/relacom" local="128968013840000000" remote="128968013840000000" />
<file name="news-pic.jpg" server="C:/wamp/www/relacom" local="128968012860000000" remote="128968012860000000" />
<file name="ContactUsPageImage.jpg" server="C:/wamp/www/relacom" local="129886020761324514" remote="129886020760000000" />
<file name="service-main.jpg" server="C:/wamp/www/relacom" local="129886066039484277" remote="129886066030000000" />
<file name="products.jpg" server="C:/wamp/www/relacom" local="129886150043049006" remote="129886150040000000" />
<file name="support.jpg" server="C:/wamp/www/relacom" local="129886159146719706" remote="129886159140000000" />
<file name="bottom-bnr.jpg" server="C:/wamp/www/relacom" local="129886253131655337" remote="129886253130000000" />
<file name="RTL-logo.jpg" server="C:/wamp/www/relacom" local="129886266339780798" remote="129886266330000000" />
<file name="about-us.jpg" server="C:/wamp/www/relacom" local="129886386089074963" remote="129886386080000000" />
<file name="service2.jpg" server="C:/wamp/www/relacom" local="129886415017899597" remote="129886415010000000" />
<file name="RTL-logo.jpg" server="C:/wamp/www/relacom/" local="129887210234594849" remote="129887210230000000" />
<file name="service2.jpg" server="C:/wamp/www/relacom/" local="129886415017899597" remote="129886415010000000" />
<file name="bottom-bnr.jpg" server="C:/wamp/www/relacom/" local="129886253131655337" remote="129886253130000000" />
<file name="products2.jpg" server="C:/wamp/www/relacom/" local="129886975808816461" remote="129886975800000000" />
<file name="support2.jpg" server="C:/wamp/www/relacom/" local="129887017636988896" remote="129887017630000000" />
<file name="rates.jpg" server="C:/wamp/www/relacom/" local="129887059311402536" remote="129887059310000000" />
<file name="myLogo.png" server="C:/wamp/www/relacom/" local="129853763207148432" remote="129853763200000000" />
<file name="myPageLogo.png" server="C:/wamp/www/relacom/" local="129854134823232326" remote="129854134820000000" />
<file name="products2.jpg" server="C:/wamp/www/relacom" local="129886975808816461" remote="129886975800000000" />
<file name="support2.jpg" server="C:/wamp/www/relacom" local="129887017636988896" remote="129887017630000000" />
<file name="rates.jpg" server="C:/wamp/www/relacom" local="129887059311402536" remote="129887059310000000" />
<file name="ContactUsPageImage.jpg" server="C:/wamp/www/relacom/" local="129886020761324514" remote="129886020760000000" />
<file name="service-main.jpg" server="C:/wamp/www/relacom/" local="129886066039484277" remote="129886066030000000" />
<file name="products.jpg" server="C:/wamp/www/relacom/" local="129886150043049006" remote="129886150040000000" />
<file name="support.jpg" server="C:/wamp/www/relacom/" local="129886159146719706" remote="129886159140000000" />
<file name="about-us.jpg" server="C:/wamp/www/relacom/" local="129886386089074963" remote="129886386080000000" />
<file name="rtl.ico" server="C:/wamp/www/relacom/" local="130055349189638210" remote="130055349180000000" />
</dwsync>